{
  "parent": "minecraft:recipes/root",
  "criteria": {
    "has_fluid_reservoir": {
      "conditions": {
        "items": [
          {
            "items": [
              "create_dd:fluid_reservoir"
            ]
          }
        ]
      },
      "trigger": "minecraft:inventory_changed"
    },
    "has_the_recipe": {
      "conditions": {
        "recipe": "create_dd:fluid_tank_from_fluid_reservoir_stonecutting"
      },
      "trigger": "minecraft:recipe_unlocked"
    }
  },
  "requirements": [
    [
      "has_fluid_reservoir",
      "has_the_recipe"
    ]
  ],
  "rewards": {
    "recipes": [
      "create_dd:fluid_tank_from_fluid_reservoir_stonecutting"
    ]
  }
}