{
  "parent": "minecraft:recipes/root",
  "criteria": {
    "has_cyan_rubber_decor": {
      "conditions": {
        "items": [
          {
            "tag": "create_dd:cyan_rubber_decor"
          }
        ]
      },
      "trigger": "minecraft:inventory_changed"
    },
    "has_the_recipe": {
      "conditions": {
        "recipe": "create_dd:cyan_padded_mosaic_rubber_from_cyan_rubber_decor_stonecutting"
      },
      "trigger": "minecraft:recipe_unlocked"
    }
  },
  "requirements": [
    [
      "has_cyan_rubber_decor",
      "has_the_recipe"
    ]
  ],
  "rewards": {
    "recipes": [
      "create_dd:cyan_padded_mosaic_rubber_from_cyan_rubber_decor_stonecutting"
    ]
  }
}