{
	"credit": "Made with Blockbench",
	"parent": "block/block",
	"textures": {
		"0": "create:block/brass_casing_connected",
		"1": "create:block/brass_gearbox",
		"particle": "create:block/axis",
		"1_0": "create:block/axis",
		"1_1": "create:block/axis_top"
	},
	"elements": [
		{
			"name": "Axis",
			"from": [0.0625, 6, 6],
			"to": [16, 10, 10],
			"rotation": {"angle": 0, "axis": "y", "origin": [16, 0, 0]},
			"faces": {
				"north": {"uv": [6, 0, 10, 16], "rotation": 270, "texture": "#1_0"},
				"east": {"uv": [6, 6, 10, 10], "rotation": 180, "texture": "#1_1"},
				"south": {"uv": [6, 0, 10, 16], "rotation": 90, "texture": "#1_0"},
				"up": {"uv": [6, 0, 10, 16], "rotation": 90, "texture": "#1_0"},
				"down": {"uv": [6, 0, 10, 16], "rotation": 90, "texture": "#1_0"}
			}
		},
		{
			"name": "Axis",
			"from": [6, 6, 0],
			"to": [10, 10, 15.9375],
			"rotation": {"angle": 0, "axis": "y", "origin": [16, 0, 0]},
			"faces": {
				"north": {"uv": [6, 6, 10, 10], "rotation": 270, "texture": "#1_1"},
				"east": {"uv": [6, 0, 10, 16], "rotation": 90, "texture": "#1_0"},
				"west": {"uv": [6, 0, 10, 16], "rotation": 270, "texture": "#1_0"},
				"up": {"uv": [6, 0, 10, 16], "texture": "#1_0"},
				"down": {"uv": [6, 0, 10, 16], "rotation": 180, "texture": "#1_0"}
			}
		},
		{
			"name": "Core",
			"from": [0.95, 1, 0.95],
			"to": [15.05, 15, 15.05],
			"rotation": {"angle": 0, "axis": "y", "origin": [16, 0, 0]},
			"faces": {
				"north": {"uv": [1, 1, 15, 15], "texture": "#1"},
				"east": {"uv": [1, 1, 15, 15], "texture": "#1"}
			}
		},
		{
			"name": "Top",
			"from": [0, 0, 0],
			"to": [2, 16, 16],
			"rotation": {"angle": 0, "axis": "y", "origin": [16, 0, 0]},
			"faces": {
				"north": {"uv": [1.75, 0, 2, 2], "texture": "#0"},
				"east": {"uv": [0, 0, 2, 2], "texture": "#0"},
				"west": {"uv": [0, 0, 2, 2], "texture": "#0"}
			}
		},
		{
			"name": "Top",
			"from": [0, 0, 14],
			"to": [16, 16, 16],
			"rotation": {"angle": 0, "axis": "y", "origin": [16, 0, 0]},
			"faces": {
				"north": {"uv": [0, 0, 2, 2], "texture": "#0"},
				"east": {"uv": [0, 0, 0.25, 2], "texture": "#0"},
				"south": {"uv": [0, 0, 2, 2], "texture": "#0"}
			}
		},
		{
			"name": "Bottom",
			"from": [0, 0, 0],
			"to": [16, 2, 16],
			"rotation": {"angle": 0, "axis": "y", "origin": [16, 0, 0]},
			"faces": {
				"north": {"uv": [0, 1.75, 2, 2], "texture": "#0"},
				"east": {"uv": [0, 1.75, 2, 2], "texture": "#0"},
				"up": {"uv": [0, 0, 2, 2], "rotation": 90, "texture": "#0"},
				"down": {"uv": [0, 0, 2, 2], "rotation": 270, "texture": "#0"}
			}
		},
		{
			"name": "Top",
			"from": [0, 14, 0],
			"to": [16, 16, 16],
			"rotation": {"angle": 0, "axis": "y", "origin": [16, 0, 0]},
			"faces": {
				"north": {"uv": [0, 0, 2, 0.25], "texture": "#0"},
				"east": {"uv": [0, 0, 2, 0.25], "texture": "#0"},
				"up": {"uv": [0, 0, 2, 2], "rotation": 90, "texture": "#0"},
				"down": {"uv": [0, 0, 2, 2], "rotation": 270, "texture": "#0"}
			}
		}
	],
	"display": {},
	"groups": [
		{
			"name": "shaft",
			"origin": [8, 8, 8],
			"color": 0,
			"children": [0]
		},
		{
			"name": "shaft",
			"origin": [8, 8, 8],
			"color": 0,
			"children": [1]
		},
		2,
		3,
		4,
		5,
		6
	]
}